{"is":"issue","title":"New Container: Helium","body":"\u003cp\u003eWe have released a new container for \u003ca href=\"https://github.com/linuxserver/docker-helium/\"\u003eHelium\u003c/a\u003e!\u003c/p\u003e\n\u003cp\u003e\u003ca href=\"https://helium.computer/\"\u003eHelium\u003c/a\u003e is a Chromium-based web browser made for people, with love. Privacy-first with unbiased ad-blocking.\u003c/p\u003e\n","createdAt":"2026-04-16 21:00:00 +0000 UTC","lastMod":"2026-04-15 11:31:05 -0400 -0400","permalink":"https://info.linuxserver.io/issues/2026-04-16-helium/","severity":"<no value>","resolved":false,"informational":true,"resolvedAt":"<no value>","affected":["New Containers","Helium"],"filename":"2026-04-16-helium.md"}