{"is":"system","title":"Rdesktop","permalink":"https://info.linuxserver.io/affected/rdesktop/","status":"ok","pages":[{"is":"issue","title":"rdesktop Phased Deprecation Notice","createdAt":"2025-08-23 23:00:00 +0000 UTC","lastMod":"2025-08-23 16:10:52 +0100 +0100","permalink":"https://info.linuxserver.io/issues/2025-08-23-rdesktop/","severity":"<no value>","resolved":false,"informational":true,"resolvedAt":"<no value>","affected":["Deprecations","rdesktop"],"filename":"2025-08-23-rdesktop.md"},{"is":"issue","title":"New Container: Rdesktop","createdAt":"2020-02-28 00:00:00 +0000 UTC","lastMod":"2021-07-03 00:52:41 +0200 +0200","permalink":"https://info.linuxserver.io/issues/2020-02-28-rdesktop/","severity":"<no value>","resolved":false,"informational":true,"resolvedAt":"<no value>","affected":["New Containers","rdesktop"],"filename":"2020-02-28-rdesktop.md"}]}