{"is":"issue","title":"New Container: Doublecommander","body":"\u003cp\u003eWe have released a new container for \u003ca href=\"https://github.com/linuxserver/docker-doublecommander\"\u003eDoublecommander\u003c/a\u003e!\u003c/p\u003e\n\u003cp\u003e\u003ca href=\"https://doublecmd.sourceforge.io/\"\u003eDouble Commander\u003c/a\u003e is a free cross platform open source file manager with two panels side by side. It is inspired by Total Commander and features some new ideas.\u003c/p\u003e\n","createdAt":"2020-03-25 00:00:00 +0000 UTC","lastMod":"2021-07-03 00:52:41 +0200 +0200","permalink":"https://info.linuxserver.io/issues/2020-03-25-doublecommander/","severity":"<no value>","resolved":false,"informational":true,"resolvedAt":"<no value>","affected":["New Containers","doublecommander"],"filename":"2020-03-25-doublecommander.md"}