{"is":"issue","title":"New Container: WPS Office","body":"\u003cp\u003eWe have released a new container for \u003ca href=\"https://github.com/linuxserver/docker-wps-office\"\u003eWPS Office\u003c/a\u003e!\u003c/p\u003e\n\u003cp\u003e\u003ca href=\"https://www.wps.com/\"\u003eWPS Office\u003c/a\u003e is a lightweight, feature-rich comprehensive office suite with high compatibility. As a handy and professional office software, WPS Office allows you to edit files in Writer, Presentation, Spreadsheet, and PDF to improve your work efficiency.\u003c/p\u003e\n","createdAt":"2023-04-24 20:00:00 +0000 UTC","lastMod":"2023-04-24 16:13:06 +0100 +0100","permalink":"https://info.linuxserver.io/issues/2023-04-24-wps-office/","severity":"<no value>","resolved":false,"informational":true,"resolvedAt":"<no value>","affected":["New Containers","wps-office"],"filename":"2023-04-24-wps-office.md"}